{
    "icon": "star",
    "name": "aurora.story",
    "quests": [
        {
            "name": "The Tales That Bind",
            "id": "aurora.story.1",
            "objectives": [
                "Talk to Aurora in the Unwritten Realms.",
                "Explore farther in the Unwritten Realms to find the Lorekeeper.",
                "Talk to the The Lorekeeper in the Unwritten Realms.",
                "The Lorekeeper left behind a cloud of Snippets.\r\n  \u2027 Catch them! (3)",
                "Talk to Aurora.",
                "Search for the Lorekeeper in the Unwritten Realms.",
                "Talk to the Lorekeeper in the Unwritten Realms.",
                "The Lorekeeper left behind more Snippets!",
                "Catch them",
                "Search for the Lorekeeper in the Unwritten Realms.",
                "Talk to the The Lorekeeper in the Unwritten Realms.",
                "More Snippets left behind by the Lorekeeper.\r\n  \u2027 Catch them",
                "Find the Lorekeeper in the Unwritten Realms.",
                "Talk to the The Lorekeeper in the Unwritten Realms.",
                "Complete The Story of Dreamlight Valley in the Lorekeeper's pages",
                "Talk to the The Lorekeeper.",
                "Talk to the Lorekeeper.",
                "Place Aurora's House in the Storybook Vale.",
                "Use the Scrooge McDuck Sign to unlock Aurora's House.",
                "Welcome Princess Aurora to the Vale.",
                "Talk to Princess Aurora."
            ],
            "rewards": [
                "Unlock Aurora",
                "Aurora's House"
            ],
            "dlc": false,
            "friendship": 0
        }
    ]
}