{
    "icon": "star",
    "name": "moana.realm",
    "quests": [
        {
            "name": "After the Storm",
            "id": "moana.realm.1",
            "objectives": [
                "Explore the Moana Realm.",
                "Help Moana fix her canoe:\r\n  \u2027 Find 8 pieces of Wood\r\n  \u2027 Dig around the island to find 3 Silk Web",
                "Go speak to Maui atop the hill."
            ],
            "rewards": []
        },
        {
            "name": "How Far You'll Go",
            "id": "moana.realm.2",
            "objectives": [
                "Moana wants to talk to you about something she found.",
                "Examine the strange map Moana just gave you.",
                "Talk to Moana about what the Memory was hiding.",
                "Search the different areas in the sea to find something to light the way across the mist.",
                "You found a Torch to light the way.\r\n  \u2027 Bring the Torch to Moana.",
                "Navigate across the mist with Moana's help.",
                "We crossed the mist!\r\n  \u2027 Something is moving in the water. Try to catch it.",
                "Show Moana your catch.",
                "Make sure Moana is comfortable in the Village by placing Moana's Fale.",
                "Use the Scrooge McDuck sign to pay for the construction of Moana's Fale.",
                "Everything is ready for Moana. Welcome her to the Village.",
                "Talk to Moana"
            ],
            "rewards": [
                "Unlock Moana"
            ]
        }
    ]
}