{
    "name": "Cheese",
    "type": "Dairy and Oil",
    "icon": "star",
    "found": [
        [
            "Chez Remy"
        ]
    ],
    "price": 180,
    "sellPrice": 180,
    "buyPrice": 180,
    "energy": 270,
    "rarity": "none",
    "growthTime": 0,
    "water": 0,
    "yield": 0,
    "maxSpawns": 0,
    "gift": 0,
    "description": "Whether it's grilled, on macaroni, or paired with pepperoni on a pizza...nothing improves a dish like a little bit of cheese. Available at Chez Remy. \n",
    "activity": [
        "ingredient"
    ]
}